SplitticAPI/__init__.py
SplitticAPI/interdiffusion.py
SplitticAPI/meowgpt.py
SplitticAPI-1.4.2.dist-info/LICENSE
SplitticAPI-1.4.2.dist-info/METADATA
SplitticAPI-1.4.2.dist-info/WHEEL
SplitticAPI-1.4.2.dist-info/top_level.txt
SplitticAPI-1.4.2.dist-info/RECORD
