Metadata-Version: 2.1
Name: SplitticAPI
Version: 1.4.2
Summary: A Python wrapper for the SplitticAPI
Home-page: https://github.com/Mike-FreeAI/splitticapi
Author: CutyCat2000
License: MIT
License-File: LICENSE
Requires-Dist: asyncio
Requires-Dist: httpx
Requires-Dist: Pillow
Requires-Dist: requests
